cli/__init__.py
cli/main.py
dome9cli-0.1.1.dist-info/LICENSE
dome9cli-0.1.1.dist-info/METADATA
dome9cli-0.1.1.dist-info/WHEEL
dome9cli-0.1.1.dist-info/entry_points.txt
dome9cli-0.1.1.dist-info/top_level.txt
dome9cli-0.1.1.dist-info/RECORD
