Metadata-Version: 2.1
Name: dome9cli
Version: 0.1.1
Summary: Command Line Interface for Dome9  The Dome9 Command Line is a set of commands used to create and manage Dome9 resources. This tool facilitates the daily use and helps enormously to work in agile methodologies. 
Home-page: https://github.com/davidmoremad/dome9cli
Author: David Amrani Hernandez
Author-email: davidmorenomad@gmail.com
License: MIT
Project-URL: Documentation, https://github.com/davidmoremad/dome9cli/blob/master/README.md
Project-URL: Source Code, https://github.com/davidmoremad/dome9cli
Project-URL: Bug Tracker, https://github.com/davidmoremad/dome9cli/issues
Project-URL: Download, https://pypi.org/project/dome9cli/#files
Keywords: dome9 cloudguard cloud cli devops secdevops ci cybersecurity
Platform: UNKNOWN
Classifier: Development Status :: 4 - Beta
Classifier: Environment :: Console
Classifier: Intended Audience :: Developers
Classifier: Intended Audience :: System Administrators
Classifier: License :: OSI Approved :: MIT License
Classifier: Natural Language :: English
Classifier: Programming Language :: Python :: 3
Classifier: Programming Language :: Python :: 3.6
Classifier: Programming Language :: Python :: 3.7
Classifier: Programming Language :: Python :: 3.8
Classifier: Programming Language :: Python :: 3.9
Classifier: Programming Language :: Python :: 3.10
Classifier: Topic :: Security
Classifier: Topic :: Software Development
Classifier: Topic :: Software Development :: Quality Assurance
Classifier: Topic :: Software Development :: Testing
Classifier: Topic :: Software Development :: Libraries :: Python Modules
License-File: LICENSE
Requires-Dist: fire (==0.4.0)
Requires-Dist: tabulate (==0.8.9)
Requires-Dist: dome9
